cofmupy/VERSION
cofmupy/__init__.py
cofmupy/config_interface.py
cofmupy/config_parser.py
cofmupy/coordinator.py
cofmupy/graph_engine.py
cofmupy/graph_plotter.py
cofmupy/wrappers.py
cofmupy/data_storage/__init__.py
cofmupy/data_storage/base_data_storage.py
cofmupy/data_storage/file_data_storage.py
cofmupy/data_storage/storage_handler.py
cofmupy/data_stream_handler/__init__.py
cofmupy/data_stream_handler/base_data_stream_handler.py
cofmupy/data_stream_handler/csv_data_stream_handler.py
cofmupy/data_stream_handler/kafka_data_stream_handler.py
cofmupy/data_stream_handler/kafka_utils.py
cofmupy/data_stream_handler/local_data_stream_handler.py
cofmupy/helpers/__init__.py
cofmupy/helpers/construct_config.py
cofmupy/helpers/extract_fmu.py
cofmupy/master/__init__.py
cofmupy/master/default_master.py
cofmupy/server/__init__.py
cofmupy/server/app.py
cofmupy/server/services.py
cofmupy/utils/__init__.py
cofmupy/utils/fixed_point_init.py
cofmupy/utils/fmu_utils.py
cofmupy/utils/interpolate.py
cofmupy/utils/proxy.py
cofmupy/utils/types.py
cofmupy-1.0.0.dist-info/licenses/LICENSE
docs/gallery_conf.py
docs/examples/plot_00_get_started.py
docs/examples/plot_01_fmu_proxy.py
docs/examples/academic_examples/plot_00_bouncing_ball.py
docs/examples/academic_examples/plot_01_dual_mass_oscillator.py
tests/__init__.py
tests/config_parser/test_config_parser.py
tests/coordinator/test_coordinator.py
tests/coordinator/test_cosim_algorithm.py
tests/data/double_fmu.py
tests/data/internal_state_fmu.py
tests/data/math_fmu.py
tests/data/math_fmu_v3.py
tests/data/math_fmu_v3_bad.py
tests/data_stream_handler/__init__.py
tests/data_stream_handler/conftest.py
tests/data_stream_handler/mock_producer.py
tests/data_stream_handler/test_csv.py
tests/data_stream_handler/test_csv_integration.py
tests/data_stream_handler/test_kafka.py
tests/data_stream_handler/test_kafka_integration.py
tests/data_stream_handler/test_kafka_utils.py
tests/data_stream_handler/test_local.py
tests/data_stream_handler/test_local_integration.py
cofmupy-1.0.0.dist-info/METADATA
cofmupy-1.0.0.dist-info/WHEEL
cofmupy-1.0.0.dist-info/entry_points.txt
cofmupy-1.0.0.dist-info/top_level.txt
cofmupy-1.0.0.dist-info/RECORD
