Metadata-Version: 2.4
Name: cofmupy
Version: 1.0.0
Summary: FMUs co-simulation in Python
Home-page: https://github.com/IRT-Saint-Exupery/CoFmuPy
Author: IRT Saint Exupéry - HECATE project team
License: BSD-2-Clause
Classifier: Programming Language :: Python :: 3
Classifier: Operating System :: OS Independent
Obsoletes: cofmpy
Requires-Python: >=3.9
License-File: LICENSE
Requires-Dist: altair==4.0.0
Requires-Dist: confluent-kafka
Requires-Dist: dotmap==1.3.30
Requires-Dist: flask==3.1.2
Requires-Dist: flask-cors==6.0.1
Requires-Dist: flask-socketio==5.5.1
Requires-Dist: fmpy==0.3.20
Requires-Dist: joblib
Requires-Dist: matplotlib
Requires-Dist: networkx==3.2.1
Requires-Dist: numpy
Requires-Dist: pandas
Requires-Dist: plotly
Requires-Dist: pythonfmu==0.6.3
Requires-Dist: pythonfmu3==0.3.3
Requires-Dist: scikit-learn
Requires-Dist: scipy
Requires-Dist: streamlit==1.12.0
Requires-Dist: tqdm
Requires-Dist: nbformat>=4.2.0
Provides-Extra: dev
Requires-Dist: black; extra == "dev"
Requires-Dist: pre-commit; extra == "dev"
Requires-Dist: pylint; extra == "dev"
Requires-Dist: pytest; extra == "dev"
Requires-Dist: pytest-cov; extra == "dev"
Requires-Dist: tox; extra == "dev"
Requires-Dist: mkdocs; extra == "dev"
Requires-Dist: mkdocs-material; extra == "dev"
Requires-Dist: mkdocstrings[python]; extra == "dev"
Requires-Dist: mkdocs-gallery; extra == "dev"
Dynamic: author
Dynamic: classifier
Dynamic: description
Dynamic: description-content-type
Dynamic: home-page
Dynamic: license
Dynamic: license-file
Dynamic: obsoletes
Dynamic: provides-extra
Dynamic: requires-dist
Dynamic: requires-python
Dynamic: summary
